droopescan-1.45.1.data/scripts/droopescan
dscan/__init__.py
dscan/droopescan.py
dscan/droopescan_completion
dscan/__pycache__/__init__.cpython-35.pyc
dscan/__pycache__/droopescan.cpython-35.pyc
dscan/common/__init__.py
dscan/common/enum.py
dscan/common/exceptions.py
dscan/common/functions.py
dscan/common/http.py
dscan/common/output.py
dscan/common/plugins_util.py
dscan/common/release_api.py
dscan/common/testutils.py
dscan/common/update_api.py
dscan/common/versions.py
dscan/common/versions.xsd
dscan/common/__pycache__/__init__.cpython-35.pyc
dscan/common/__pycache__/enum.cpython-35.pyc
dscan/common/__pycache__/exceptions.cpython-35.pyc
dscan/common/__pycache__/functions.cpython-35.pyc
dscan/common/__pycache__/http.cpython-35.pyc
dscan/common/__pycache__/output.cpython-35.pyc
dscan/common/__pycache__/plugins_util.cpython-35.pyc
dscan/common/__pycache__/release_api.cpython-35.pyc
dscan/common/__pycache__/testutils.cpython-35.pyc
dscan/common/__pycache__/update_api.cpython-35.pyc
dscan/common/__pycache__/versions.cpython-35.pyc
dscan/common/template/droopescan.mustache
dscan/common/template/enumerate_cms.mustache
dscan/common/template/enumerate_interesting.mustache
dscan/common/template/enumerate_plugins.mustache
dscan/common/template/enumerate_version.mustache
dscan/common/template/help_enumerate.mustache
dscan/common/template/help_epilog.mustache
dscan/common/template/help_method.mustache
dscan/common/template/intro.mustache
dscan/common/template/scan_begin.mustache
dscan/common/template/stats_plugin.mustache
dscan/plugins/__init__.py
dscan/plugins/drupal.py
dscan/plugins/example.py
dscan/plugins/joomla.py
dscan/plugins/moodle.py
dscan/plugins/release.py
dscan/plugins/silverstripe.py
dscan/plugins/stats.py
dscan/plugins/tests.py
dscan/plugins/update.py
dscan/plugins/wordpress.py
dscan/plugins/__pycache__/__init__.cpython-35.pyc
dscan/plugins/__pycache__/drupal.cpython-35.pyc
dscan/plugins/__pycache__/joomla.cpython-35.pyc
droopescan-1.45.1.dist-info/LICENSE
droopescan-1.45.1.dist-info/METADATA
droopescan-1.45.1.dist-info/WHEEL
droopescan-1.45.1.dist-info/top_level.txt
droopescan-1.45.1.dist-info/RECORD
