Metadata-Version: 2.1
Name: droopescan
Version: 1.45.1
Summary: A plugin-based scanner that aids security researchers in identifying issues with several CMSs: Drupal, Wordpress, Moodle and SilverStripe. https://github.com/droope/droopescan
Home-page: http://github.com/droope/droopescan/
Author: Pedro Worcel
Author-email: pedro@worcel.com
License: GPL
Platform: UNKNOWN
Classifier: Development Status :: 5 - Production/Stable
Classifier: License :: OSI Approved :: GNU General Public License (GPL)
Classifier: Operating System :: Unix
Classifier: Programming Language :: Python :: 2.7
Classifier: Programming Language :: Python :: 3
Requires-Dist: cement (<2.6.99,>=2.6)
Requires-Dist: pystache
Requires-Dist: requests
Requires-Dist: futures ; python_version == "2.7"
